Workbook

Sheet CAPA Explicações
B1: Facilite ainda mais o seu trabalho
B2: Conheça o aplicativo para o controle do condomínio usado em mais de 20 mil condomínios no Brasil, Estados Unidos, Canadá e México.
B3: INSTRUÇÕES
B5: Nome da aba | C5: Orientações
B6: Fluxo de caixa | C6: Esta aba serve para você controlar o fluxo de caixa e acompanhar o saldo do condomínio mês a mês. Na parte de receitas, você lista todas as fontes e valores de receita do condomínio. É possível adicionar linhas, caso haja mais fontes de renda. Em Outras Contas você deve atualizar o saldo de outras contas do condomínio. Em Despesas, adicione todas as despesas de valor fixo e que acontecem todo o mês. Em despesas variáveis, as despesas que tem custos diferentes todos os meses. Em Saldo Atual, você conseguirá verificar os saldos de cada conta do condomínio.
B8: Manutenções | C8: Aqui você consegue listar todos os itens por área do condomínio que precisam ser verificados de modo periódico e controlar as datas de manutenção de cada item.
B10: Controle de visitantes | C10: Para mais segurança no condomínio, insira as informações de todos os visitantes e prestadores de serviço com data e horário de entrada e saída do condomínio. No caso de prestadores de serviço, você deve adicionar também o nome da empresa daquele prestador de serviço.
B12: Reservas | C12: Para controlar as reservas, utilize apenas este calendário para reserva de dependências do condomínio. Adicione nome do morador, unidade e qual dependência ele está reservando.
B14: Escala de funcionários | C14: Para organizar os horários de trabalho dos funcionários, liste primeiro todos os funcionários. Após, pinte o quadrado com o dia e turno que ele estará trabalhando. Coloque um "F" nos dias e turnos que ele estará de folga. Você pode editar as informações de turnos de trabalho de acordo com o que acontece no seu condomínio.
B16: Funcionários e lançamento de férias | C16: As abas Funcionários e Lançamentos de férias são interligadas. Ou seja, funcionam de modo conjunto. Para controle de férias e funcionários, você deve adicionar o nome do funcionário e a data de início. Quando este solicitar férias, você deve selecioná-lo na aba Lançamento de férias, adicionar a data de início e final de férias. A planilha calculará o saldo atual de férias daquele funcionário.

Sheet Fluxo de caixa 2024
B1: Planilha Financeira do Condomínio: | D1: FERNANDO LONA
B2: Responsável: | D2: crisjessi10@icloud.com | G2: Ano de Referência: | H2: 2024
A5: Mês | B5: =CONCATENATE("Janeiro/",$H$2) -> Janeiro/2024 | C5: =CONCATENATE("Fevereiro/",$H$2) -> Fevereiro/2024 | D5: =CONCATENATE("Março/",$H$2) -> Março/2024 | E5: =CONCATENATE("Abril/",$H$2) -> Abril/2024 | F5: =CONCATENATE("Maio/",$H$2) -> Maio/2024 | G5: =CONCATENATE("Junho/",$H$2) -> Junho/2024 | H5: =CONCATENATE("Julho/",$H$2) -> Julho/2024 | I5: =CONCATENATE("Agosto/",$H$2) -> Agosto/2024 | J5: =CONCATENATE("Setembro/",$H$2) -> Setembro/2024 | K5: =CONCATENATE("Outubro/",$H$2) -> Outubro/2024 | L5: =CONCATENATE("Novembro/",$H$2) -> Novembro/2024 | M5: =CONCATENATE("Dezembro/",$H$2) -> Dezembro/2024
A6: SALDO Total (Caixa) | B6: 0 | C6: =B6+B31 -> 0 | D6: =C6+C31 -> 393.46 | E6: =D31 -> 301.13 | F6: =E31 -> 637.75 | G6: =F31+G8-G16 -> 1530.22 | H6: =H8-H16+G31 -> 2030.22 | I6: =I8+H31-I16 -> 2460.27 | J6: =J8+I31-J16 -> 2832.6 | K6: =K8+J31-K16 -> 3177.3 | L6: =K31+L8-L16-L21 -> 3363.27 | M6: =L31+M8-M16-M21 -> 3817.17
A8: RECEITAS | B8: =SUM(B9:B11) -> 0 | C8: =C9 -> 600 | D8: =D9 -> 600 | E8: =E9 -> 600 | F8: =SUM(F9:F11) -> 600 | G8: =SUM(G9:G11) -> 600 | H8: =SUM(H9:H11) -> 600 | I8: =SUM(I9:I11) -> 600 | J8: =SUM(J9:J11) -> 600 | K8: =SUM(K9:K11) -> 600 | L8: =SUM(L9:L11) -> 600 | M8: =SUM(M9:M11) -> 600
A9: Cotas Condominiais (Até dia 08) | B9: 0 | C9: 600 | D9: 600 | E9: =TaxaCondominio!E10 -> 600 | F9: =TaxaCondominio!F10 -> 600 | G9: =TaxaCondominio!G10 -> 600 | H9: =TaxaCondominio!H10 -> 600 | I9: =TaxaCondominio!I10 -> 600 | J9: =TaxaCondominio!J10 -> 600 | K9: =TaxaCondominio!K10 -> 600 | L9: =TaxaCondominio!L10 -> 600 | M9: =TaxaCondominio!M10 -> 600
A10: Rendimentos | B10: 0
A13: DESPESAS FIXAS | B13: =SUM(B14:B15) -> 0 | C13: =C14 -> 0 | D13: =SUM(D14:D15) -> 0 | E13: =SUM(E14:E15) -> 0 | F13: =SUM(F14:F15) -> 0 | G13: =SUM(G14:G15) -> 0 | H13: =SUM(H14:H15) -> 0 | I13: =SUM(I14:I15) -> 0 | J13: =SUM(J14:J15) -> 0 | K13: =SUM(K14:K15) -> 0 | ... M13: =SUM(M14:M15) -> 0
A14: Outras
A16: DESPESAS VARIÁVEIS | B16: =B17+B18+B19 -> 0 | C16: =C17+C18+C19 -> 126.72 | D16: =SUM(D17:D20) -> 335.63 | E16: =SUM(E17:E20) -> 263.38 | F16: =SUM(F17:F20) -> 100 | G16: =SUM(G17:G20) -> 207.53 | H16: =SUM(H17:H20) -> 100 | I16: =SUM(I17:I20) -> 169.95 | J16: =SUM(J17:J20) -> 227.67 | K16: =SUM(K17:K20) -> 131.46 | ... M16: =SUM(M17:M20) -> 135.6
A17: Água (venc. Dia 10) | B17: 0 | C17: 72.05 | D17: 235.63 | E17: 61.59 | I17: 76.62 | J17: 76.3 | K17: 76.3 | L17: 76.3 | M17: 76.3
A18: Luz (venc. Dia 21) | B18: 0 | C18: 54.67 | D18: 0 | E18: 101.79 | F18: 0 | G18: 107.53 | H18: 0 | I18: 93.33 | J18: 51.37 | K18: 55.16 | L18: 63.93 | M18: 59.3
A19: Faxina | B19: 0 | C19: 0 | D19: 100 | E19: 100 | F19: 100 | G19: 100 | H19: 100 | J19: 100 | L19: 100
A21: DESPESAS EXTRAS | B21: =B22+B23+B24 -> 0 | C21: =SUM(C22:C25) -> 79.82 | D21: =SUM(D22:D25) -> 356.7 | E21: =SUM(E22:E25) -> 0 | F21: =SUM(F22:F25) -> 0 | G21: =SUM(G22:G25) -> 0 | H21: =SUM(H22:H25) -> 0 | I21: =SUM(I22:I25) -> 0 | J21: =SUM(J22:J25) -> 123.84 | ... M21: =SUM(M22:M25) -> 10.5
A22: Obras | B22: 0 | C22: 0 | D22: 180
A23: Consertos | B23: 0
A24: Outras | B24: 0 | C24: 79.82 | D24: 176.7 | J24: 123.84 | L24: 173.8 | M24: 10.5
A26: SALDO DETALHADO - BALANCETE
A27: Receitas | B27: =B8 -> 0 | C27: =C8 -> 600 | D27: =D8+D6 -> 993.46 | E27: =E8+D31 -> 901.13 | F27: =F8+E31 -> 1237.75 | G27: =G8+F31 -> 1737.75 | H27: =H8+G31 -> 2130.22 | I27: =I8+H31 -> 2630.22 | J27: =I31+J8 -> 3060.27 | K27: =J31+K8 -> 3308.76 | L27: =K31+L8 -> 3777.3 | M27: =L31+M9 -> 3963.27
A28: Rendimento | B28: =B13 -> 0 | C28: =C10 -> 0 | D28: =D10 -> 0 | E28: =E10 -> 0 | F28: =F13 -> 0 | G28: =G13 -> 0 | H28: =H13 -> 0 | I28: =I13 -> 0 | J28: =J10 -> 0 | K28: =K10 -> 0 | L28: 0 | M28: =M10 -> 0
A29: Despesas Variáveis | B29: =B16 -> 0 | C29: =C16 -> 126.72 | D29: =D16 -> 335.63 | E29: =E16 -> 263.38 | F29: =F16 -> 100 | G29: =G16 -> 207.53 | H29: =H16 -> 100 | I29: =I16 -> 169.95 | ... M29: =M16 -> 135.6
A30: Despesas Extras | B30: =B21 -> 0 | C30: =C21 -> 79.82 | D30: =D21 -> 356.7 | E30: =E21 -> 0 | F30: =F21 -> 0 | G30: =G21 -> 0 | H30: =H21 -> 0 | I30: =I21 -> 0 | ... M30: =M21 -> 10.5
A31: Saldo do Mês | B31: =B27+B28-B29-B30 -> 0 | C31: =C27+C28-C29-C30 -> 393.46 | D31: =D27+D28-D29-D30 -> 301.13 | E31: =E27+E28-E29-E30 -> 637.75 | F31: =F27+F28-F29-F30 -> 1137.75 | G31: =G27+G28-G29-G30 -> 1530.22 | H31: =H27+H28-H29-H30 -> 2030.22 | I31: =I27+I28-I29-I30 -> 2460.27 | J31: =J27-J29-J30 -> 2708.76 | K31: =K27+K28-K29-K30 -> 3177.3 | L31: =L27+L28-L29-L30 -> 3363.27 | M31: =M27+M28-M29-M30 -> 3817.17

Sheet Fluxo de caixa 2025
B1: Planilha Financeira do Condomínio: | D1: FERNANDO LONA
B2: Responsável: | D2: crisjessi10@icloud.com | G2: Ano de Referência: | H2: 2025
A5: Mês | B5: =CONCATENATE("Janeiro/",$H$2) -> Janeiro/2025 | C5: =CONCATENATE("Fevereiro/",$H$2) -> Fevereiro/2025 | D5: =CONCATENATE("Março/",$H$2) -> Março/2025 | E5: =CONCATENATE("Abril/",$H$2) -> Abril/2025 | F5: =CONCATENATE("Maio/",$H$2) -> Maio/2025 | G5: =CONCATENATE("Junho/",$H$2) -> Junho/2025 | H5: =CONCATENATE("Julho/",$H$2) -> Julho/2025 | I5: =CONCATENATE("Agosto/",$H$2) -> Agosto/2025 | J5: =CONCATENATE("Setembro/",$H$2) -> Setembro/2025 | K5: =CONCATENATE("Outubro/",$H$2) -> Outubro/2025 | L5: =CONCATENATE("Novembro/",$H$2) -> Novembro/2025 | M5: =CONCATENATE("Dezembro/",$H$2) -> Dezembro/2025
A6: SALDO Total (Caixa) | B6: ='Fluxo de caixa 2024'!M31+B8-B17-B22 -> 3783.1 | C6: =B33+C8+C29+-C30 -> 4048.93 | D6: =C33+D8-D17 -> 4314.11 | E6: =D33+E8-E17 -> 3680.74 | F6: =E33+F8-F17-F22 -> 3196.89 | G6: =F33+G8-G17-G22 -> 3311.51 | H6: =H33 -> 3425.2 | I6: =I33 -> 3638.53 | J6: =J33 -> 3473.87 | K6: =K33 -> 3298.53 | L6: =L33 -> 3440.07 | M6: =M33 -> 3344
A8: RECEITAS | B8: =SUM(B9:B11) -> 600 | C8: =C9 -> 600 | D8: =D9+D10 -> 600 | E8: =E9+E10 -> 600 | F8: =SUM(F9:F11) -> 600 | G8: =SUM(G9:G11) -> 600 | H8: =SUM(H9:H11) -> 600 | I8: =SUM(I9:I11) -> 600 | J8: =SUM(J9:J11) -> 1024.06 | K8: =SUM(K9:K11) -> 664.34 | L8: =SUM(L9:L11) -> 625.33 | M8: =SUM(M9:M11) -> 620.6
A9: Cotas Condominiais (Até dia 08) | B9: =TaxaCondominio!N10 -> 600 | C9: =TaxaCondominio!O10 -> 600 | D9: =TaxaCondominio!P10 -> 600 | E9: =TaxaCondominio!Q10 -> 600 | F9: =TaxaCondominio!R10 -> 600 | G9: =TaxaCondominio!S10 -> 600 | H9: =TaxaCondominio!T10 -> 600 | I9: =TaxaCondominio!U10 -> 600 | ... M9: =TaxaCondominio!Y10 -> 600
A10: Rendimentos | J10: 424.06 | K10: 64.34 | L10: 25.33 | M10: 20.6
A13: DESPESAS FIXAS | B13: =SUM(B14:B16) -> 0 | C13: =SUM(C14:C16) -> 0 | D13: =SUM(D14:D16) -> 0 | E13: =SUM(E14:E16) -> 0 | F13: =SUM(F14:F16) -> 0 | G13: =SUM(G14:G16) -> 0 | H13: =SUM(H14:H16) -> 0 | I13: =SUM(I14:I16) -> 0 | ... M13: =SUM(M14:M16) -> 0
A14: Outras | B14: 0 | C14: 0 | D14: 0 | E14: 0 | F14: 0 | G14: 0 | H14: 0 | I14: 0 | J14: 0 | K14: 0 | L14: 0 | M14: 0
A15: IR/IOF | B15: 0 | C15: 0 | D15: 0 | E15: 0 | F15: 0 | G15: 0 | H15: 0 | I15: 0 | J15: 0 | K15: 0 | L15: 20.17 | M15: 0
A17: DESPESAS VARIÁVEIS | B17: =B18+B19+B20 -> 324.07 | C17: =C18+C19+C20 -> 334.17 | D17: =SUM(D18:D21) -> 334.82 | E17: =SUM(E18:E21) -> 233.37 | F17: =SUM(F18:F21) -> 333.85 | G17: =SUM(G18:G21) -> 335.38 | H17: =SUM(H18:H21) -> 336.31 | I17: =SUM(I18:I21) -> 236.67 | J17: =SUM(J18:J21) -> 343.72 | K17: =SUM(K18:K21) -> 344.02 | ... M17: =SUM(M18:M21) -> 336.67
A18: Água (venc. Dia 10) | B18: 76.5 | C18: 76.3 | D18: 76.3 | E18: 76.3 | F18: 76.3 | G18: 76.3 | H18: 76.3 | I18: 76.3 | J18: 76.3 | K18: 76.3 | L18: 76.3 | M18: 76.3
A19: Luz (venc. Dia 21) | B19: 47.57 | C19: 57.87 | D19: 58.52 | E19: 57.07 | F19: 57.55 | G19: 59.08 | H19: 60.01 | I19: 60.37 | J19: 67.42 | K19: 67.72 | L19: 62.65 | M19: 60.37
A20: Faxina | B20: 200 | C20: 200 | D20: 200 | E20: 100 | F20: 200 | G20: 200 | H20: 200 | I20: 100 | J20: =100+100 -> 200 | K20: 200 | L20: 200 | M20: 200
A22: DESPESAS EXTRAS | B22: =B23+B24+B25 -> 310 | C22: =SUM(C23:C26) -> 0 | D22: =SUM(D23:D26) -> 1000 | E22: =SUM(E23:E26) -> 150 | F22: =SUM(F23:F26) -> 600 | G22: =SUM(G23:G26) -> 150 | H22: =SUM(H23:H26) -> 150 | I22: =SUM(I23:I26) -> 150 | J22: =SUM(J23:J26) -> 845 | ... M22: =SUM(M23:M26) -> 380
A23: Obras | B23: 0 | C23: 0 | D23: 0 | E23: 0 | F23: 0 | G23: 0 | H23: 0 | I23: 0 | J23: 0 | K23: 0 | L23: 0 | M23: 0
A24: Consertos | B24: 310 | C24: 0 | D24: 1000 | E24: 0 | F24: 450 | G24: 0 | H24: 0 | I24: 0 | J24: =45+650 -> 695 | K24: 410 | L24: 0 | M24: 230
A25: Outras (Encanamento Garagem) | B25: 0 | C25: 0 | D25: 0 | E25: 150 | F25: 150 | G25: 150 | H25: 150 | I25: 150 | J25: 150 | K25: 150 | L25: 150 | M25: 150
A27: SALDO DETALHADO - BALANCETE
A28: Receitas | B28: ='Fluxo de caixa 2024'!M31+'Fluxo de caixa 2025'!B8 -> 4417.17 | C28: =C8+B33 -> 4383.1 | D28: =D8+C33 -> 4648.93 | E28: =E8+D33 -> 3914.11 | F28: =F8+E33 -> 4130.74 | G28: =F33+G8 -> 3796.89 | H28: =G33+H9 -> 3911.51 | I28: =I8+H33 -> 4025.2 | J28: =I33+J8 -> 4662.59 | K28: =J33+K8 -> 4138.21 | L28: =K33+L8 -> 3923.86 | M28: =L33+M8 -> 4060.67
A29: Rendimento | B29: =B10 -> 0 | C29: =C10 -> 0 | D29: =D10 -> 0 | E29: =E10 -> 0 | F29: =F13 -> 0 | G29: 0 | H29: =H10 -> 0 | I29: =I13 -> 0 | J29: =J10 -> 424.06 | K29: =K10 -> 64.34 | L29: =L10 -> 25.33 | M29: =M10 -> 20.6
A30: Despesas Variáveis | B30: =B17 -> 324.07 | C30: =C17 -> 334.17 | D30: =D17 -> 334.82 | E30: =E17 -> 233.37 | F30: =F17 -> 333.85 | G30: =G17 -> 335.38 | H30: =H17 -> 336.31 | I30: =I17 -> 236.67 | ... M30: =M17 -> 336.67
A31: Despesas Extras | B31: =B22 -> 310 | C31: =C22 -> 0 | D31: =D22 -> 1000 | E31: =E22 -> 150 | F31: =F22 -> 600 | G31: =G22 -> 150 | H31: =H22 -> 150 | I31: =I22 -> 150 | ... M31: =M22 -> 380
A32: Despesas Fixas | B32: =B13 -> 0 | C32: =C13 -> 0 | D32: =D13 -> 0 | E32: =E13 -> 0 | F32: =F13 -> 0 | G32: =G13 -> 0 | H32: =H13 -> 0 | I32: =I13 -> 0 | ... L32: =L13 -> 20.17 | M32: =M23 -> 0
A33: Saldo do Mês | B33: =B28-B30-B31-B32 -> 3783.1 | C33: =C28-C30-C31-C32 -> 4048.93 | D33: =D28-D30-D31-D32 -> 3314.11 | E33: =E28-E30-E31-E32 -> 3530.74 | F33: =F28-F30-F31-F32 -> 3196.89 | G33: =G28-G30-G31-G32 -> 3311.51 | H33: =H28-H30-H31-H32 -> 3425.2 | I33: =I28-I30-I31-I32 -> 3638.53 | J33: =J28-J30-J31 -> 3473.87 | K33: =K28+K29-K30-K31 -> 3298.53 | L33: =L28+L29-L30-L31-L32 -> 3440.07 | M33: =M28-M30-M31 -> 3344
A35: despesa Fabricio | D35: -3000 | E35: =D35+E25 -> -2850 | F35: =SUM(E35+F25) -> -2700 | G35: =SUM(F35+G25) -> -2550 | H35: =SUM(G35+H22) -> -2400 | I35: =H35+150 -> -2250 | J35: =I35+150 -> -2100 | K35: =J35+150 -> -1950 | L35: =K35+150 -> -1800 | M35: =L35+150 -> -1650

Sheet Fluxo de caixa 2026
B1: Planilha Financeira do Condomínio: | D1: FERNANDO LONA
B2: Responsável: | D2: crisjessi10@icloud.com | G2: Ano de Referência: | H2: 2026
A5: Mês | B5: =CONCATENATE("Janeiro/",$H$2) -> Janeiro/2026 | C5: =CONCATENATE("Fevereiro/",$H$2) -> Fevereiro/2026 | D5: =CONCATENATE("Março/",$H$2) -> Março/2026 | E5: =CONCATENATE("Abril/",$H$2) -> Abril/2026 | F5: =CONCATENATE("Maio/",$H$2) -> Maio/2026 | G5: =CONCATENATE("Junho/",$H$2) -> Junho/2026 | H5: =CONCATENATE("Julho/",$H$2) -> Julho/2026 | I5: =CONCATENATE("Agosto/",$H$2) -> Agosto/2026 | J5: =CONCATENATE("Setembro/",$H$2) -> Setembro/2026 | K5: =CONCATENATE("Outubro/",$H$2) -> Outubro/2026 | L5: =CONCATENATE("Novembro/",$H$2) -> Novembro/2026 | M5: =CONCATENATE("Dezembro/",$H$2) -> Dezembro/2026
A6: SALDO Total (Caixa) | B6: ='Fluxo de caixa 2025'!M33+B8-B17-B22 -> 2634.45 | C6: =C33 -> 2733.21 | D6: =D33 -> 2794.29 | E6: =E33 -> 3124.35 | F6: =F33 -> 2633.16
A8: RECEITAS | B8: =SUM(B9:B11) -> 636.1 | C8: =C9 -> 600 | D8: =D9+D10 -> 656.21 | E8: =E9+E10 -> 624.97 | F8: =SUM(F9:F11) -> 635.12 | G8: =SUM(G9:G11) -> 605.56 | H8: =SUM(H9:H11) -> 0 | I8: =SUM(I9:I11) -> 0 | J8: =SUM(J9:J11) -> 0 | K8: =SUM(K9:K11) -> 0 | L8: =SUM(L9:L11) -> 0 | M8: =SUM(M9:M11) -> 0
A9: Cotas Condominiais (Até dia 08) | B9: =TaxaCondominio!Z10 -> 600 | C9: =TaxaCondominio!AA10 -> 600 | D9: =TaxaCondominio!AB10 -> 600 | E9: =TaxaCondominio!AC10 -> 600 | F9: =TaxaCondominio!AD10 -> 600 | G9: =TaxaCondominio!AE10 -> 600 | H9: =TaxaCondominio!AF10 -> 0 | I9: =TaxaCondominio!AG10 -> 0 | ... M9: =TaxaCondominio!AK10 -> 0
A10: Rendimentos | B10: 36.1 | C10: 27.74 | D10: 56.21 | E10: 24.97 | F10: 35.12 | G10: 5.56
A13: DESPESAS FIXAS | B13: =SUM(B14:B16) -> 0 | C13: =SUM(C14:C16) -> 0 | D13: =SUM(D14:D16) -> 0 | E13: =SUM(E14:E16) -> 0 | F13: =SUM(F14:F16) -> 0 | G13: =SUM(G14:G16) -> 0 | H13: =SUM(H14:H16) -> 0 | I13: =SUM(I14:I16) -> 0 | ... M13: =SUM(M14:M16) -> 0
A14: Outras | B14: 0 | C14: 0 | D14: 0 | E14: 0 | F14: 0 | G14: 0 | H14: 0 | I14: 0 | J14: 0 | K14: 0 | L14: 0 | M14: 0
A15: IR/IOF | B15: 0 | C15: 0 | D15: 0 | E15: 0 | F15: 0 | G15: 0 | H15: 0 | I15: 0 | J15: 0 | K15: 0 | L15: 0 | M15: 0
A17: DESPESAS VARIÁVEIS | B17: =B18+B19+B20 -> 345.65 | C17: =C18+C19+C20 -> 351.24 | D17: =SUM(D18:D21) -> 145.13 | E17: =SUM(E18:E21) -> 144.91 | F17: =SUM(F18:F21) -> 976.31 | G17: =SUM(G18:G21) -> 445.96 | H17: =SUM(H18:H21) -> 0 | I17: =SUM(I18:I21) -> 0 | J17: =SUM(J18:J21) -> 0 | K17: =SUM(K18:K21) -> 0 | ... M17: =SUM(M18:M21) -> 0
A18: Água (venc. Dia 10) | B18: 80.22 | C18: 81.25 | D18: 81.24 | E18: 81.24 | F18: 81.24 | G18: 81.24 | H18: 0 | I18: 0 | J18: 0 | K18: 0 | L18: 0 | M18: 0
A19: Luz (venc. Dia 21) | B19: 65.43 | C19: 69.99 | D19: 63.89 | E19: 63.67 | F19: 64.68 | G19: 64.72 | H19: 0 | I19: 0 | J19: 0 | K19: 0 | L19: 0 | M19: 0
A20: Faxina | B20: 200 | C20: 200 | D20: 0 | E20: 0 | F20: =150 + 150 + 399 + 131.39 -> 830.39 | G20: 300 | H20: 0 | I20: 0 | J20: 0 | K20: 0 | L20: 0 | M20: 0
A22: DESPESAS EXTRAS | B22: =B23+B24+B25 -> 1000 | C22: =SUM(C23:C26) -> 150 | D22: =SUM(D23:D26) -> 450 | E22: =SUM(E23:E26) -> 150 | F22: =SUM(F23:F26) -> 150 | G22: =SUM(G23:G26) -> 2353.24 | H22: =SUM(H23:H26) -> 0 | I22: =SUM(I23:I26) -> 0 | J22: =SUM(J23:J26) -> 0 | ... M22: =SUM(M23:M26) -> 0
A23: Obras | B23: 0 | C23: 0 | D23: 300 | E23: 0 | F23: 0 | G23: =1500 + 673.24 -> 2173.24 | H23: 0 | I23: 0 | J23: 0 | K23: 0 | L23: 0 | M23: 0
A24: Consertos | B24: 850 | C24: 0 | D24: 0 | E24: 0 | F24: 0 | G24: 180 | H24: 0 | I24: 0 | J24: 0 | K24: 0 | L24: 0 | M24: 0
A25: Outras (Encanamento Garagem) | B25: 150 | C25: 150 | D25: 150 | E25: 150 | F25: 150 | G25: 0 | L25: 0 | M25: 0
A27: SALDO DETALHADO - BALANCETE
A28: Receitas | B28: ='Fluxo de caixa 2025'!M33+'Fluxo de caixa 2026'!B8 -> 3980.1 | C28: =B33+C8 -> 3234.45 | D28: =C33+D8 -> 3389.42 | E28: =D33+E8 -> 3419.26 | F28: =E33+F8 -> 3759.47 | G28: =F33+G8 -> 3238.72 | H28: =G33+H8 -> 439.52 | I28: 0 | J28: 0 | K28: 0 | L28: 0 | M28: 0
A29: Rendimento | B29: =B10 -> 36.1 | C29: =C10 -> 27.74 | D29: =D10 -> 56.21 | E29: =E10 -> 24.97 | F29: =F10 -> 35.12 | G29: =G10 -> 5.56 | H29: =H10 -> 0 | I29: =I13 -> 0 | J29: =J10 -> 0 | K29: =K10 -> 0 | L29: =L10 -> 0 | M29: =M10 -> 0
A30: Despesas Variáveis | B30: =B17 -> 345.65 | C30: =C17 -> 351.24 | D30: =D17 -> 145.13 | E30: =E17 -> 144.91 | F30: =F17 -> 976.31 | G30: =G17 -> 445.96 | H30: =H17 -> 0 | I30: =I17 -> 0 | ... M30: =M17 -> 0
A31: Despesas Extras | B31: =B22 -> 1000 | C31: =C22 -> 150 | D31: =D22 -> 450 | E31: =E22 -> 150 | F31: =F22 -> 150 | G31: =G22 -> 2353.24 | H31: =H22 -> 0 | I31: =I22 -> 0 | ... M31: =M22 -> 0
A32: Despesas Fixas | B32: =B13 -> 0 | C32: =C13 -> 0 | D32: =D13 -> 0 | E32: =E13 -> 0 | F32: =F13 -> 0 | G32: =G13 -> 0 | H32: =H13 -> 0 | I32: =I13 -> 0 | ... L32: =L13 -> 0 | M32: =M23 -> 0
A33: Saldo do Mês | B33: =B28-B30-B31-B32 -> 2634.45 | C33: =C28-C30-C31-C32 -> 2733.21 | D33: =D28-D30-D31-D32 -> 2794.29 | E33: =E28-E30-E31-E32 -> 3124.35 | F33: =F28-F30-F31-F32 -> 2633.16 | G33: =G28-G30-G31-G32 -> 439.52 | H33: =H28-H30-H31-H32 -> 439.52 | I33: =I28-I30-I31-I32 -> 0 | J33: =J28-J30-J31 -> 0 | K33: =K28+K29-K30-K31 -> 0 | L33: =L28+L29-L30-L31-L32 -> 0 | M33: =M28-M30-M31 -> 0
A35: despesa Fabricio | B35: ='Fluxo de caixa 2025'!M35 + B25 -> -1500 | C35: =B35+150 -> -1350 | D35: =C35+150 -> -1200 | E35: =D35+150 -> -1050 | F35: =E35+150 -> -900

Sheet TaxaCondominio
A1: Informações detalhadas sobre o pagamento do condomínio
A2: Número de apartamentos: | B2: 4
A4: Apartamento | B4: =CONCATENATE("Janeiro/",'Fluxo de caixa 2024'!$H$2) -> Janeiro/2024 | C4: =CONCATENATE("Fevereiro/",'Fluxo de caixa 2024'!$H$2) -> Fevereiro/2024 | D4: =CONCATENATE("Março/",'Fluxo de caixa 2024'!$H$2) -> Março/2024 | E4: =CONCATENATE("Abril/",'Fluxo de caixa 2024'!$H$2) -> Abril/2024 | F4: =CONCATENATE("Maio/",'Fluxo de caixa 2024'!$H$2) -> Maio/2024 | G4: =CONCATENATE("Junho/",'Fluxo de caixa 2024'!$H$2) -> Junho/2024 | H4: =CONCATENATE("Julho/",'Fluxo de caixa 2024'!$H$2) -> Julho/2024 | I4: =CONCATENATE("Agosto/",'Fluxo de caixa 2024'!$H$2) -> Agosto/2024 | J4: =CONCATENATE("Setembro/",'Fluxo de caixa 2024'!$H$2) -> Setembro/2024 | K4: =CONCATENATE("Outubro/",'Fluxo de caixa 2024'!$H$2) -> Outubro/2024 | L4: =CONCATENATE("Novembro/",'Fluxo de caixa 2024'!$H$2) -> Novembro/2024 | M4: =CONCATENATE("Dezembro/",'Fluxo de caixa 2024'!$H$2) -> Dezembro/2024 | N4: 45658 | O4: 45689 | P4: 45717 | Q4: 45748 | R4: 45778 | S4: 45809 | T4: 45839 | U4: 45870 | V4: 45901 | W4: 45931 | X4: 45962 | Y4: 45992 | Z4: 46023 | AA4: 46054 | AB4: 46082 | AC4: 46113 | AD4: 46143 | AE4: 46174
A5: 1 | B5: 0 | C5: 150 | D5: 150 | E5: 150 | F5: 150 | G5: 150 | H5: 150 | I5: 150 | J5: 150 | K5: 150 | L5: 150 | M5: 150 | N5: 150 | O5: 150 | P5: 150 | Q5: 150 | R5: 150 | S5: 150 | T5: 150 | U5: 150 | V5: 150 | W5: 150 | X5: 150 | Y5: 150 | Z5: 150 | AA5: 150 | AB5: 150 | AC5: 150 | AD5: 150 | AE5: 0
A6: 2 | B6: 0 | C6: 150 | D6: 150 | E6: 150 | F6: 150 | G6: 150 | H6: 150 | I6: 150 | J6: 150 | K6: 150 | L6: 150 | M6: 150 | N6: 150 | O6: 150 | P6: 150 | Q6: 150 | R6: 150 | S6: 150 | T6: 150 | U6: 150 | V6: 150 | W6: 150 | X6: 150 | Y6: 150 | Z6: 150 | AA6: 150 | AB6: 150 | AC6: 150 | AD6: 150 | AE6: 200
A7: 3 | B7: 0 | C7: 150 | D7: 150 | E7: 150 | F7: 150 | G7: 150 | H7: 150 | I7: 150 | J7: 150 | K7: 150 | L7: 150 | M7: 150 | N7: 150 | O7: 150 | P7: 150 | Q7: 150 | R7: 150 | S7: 150 | T7: 150 | U7: 150 | V7: 150 | W7: 150 | X7: 150 | Y7: 150 | Z7: 150 | AA7: 150 | AB7: 150 | AC7: 150 | AD7: 150 | AE7: 200
A8: 4 | B8: 0 | C8: 150 | D8: 150 | E8: 150 | F8: 150 | G8: 150 | H8: 150 | I8: 150 | J8: 150 | K8: 150 | L8: 150 | M8: 150 | N8: 150 | O8: 150 | P8: 150 | Q8: 150 | R8: 150 | S8: 150 | T8: 150 | U8: 150 | V8: 150 | W8: 150 | X8: 150 | Y8: 150 | Z8: 150 | AA8: 150 | AB8: 150 | AC8: 150 | AD8: 150 | AE8: 200
A10: Total | B10: =SUM(B5:B8) -> 0 | C10: =SUM(C5:C8) -> 600 | D10: =SUM(D5:D8) -> 600 | E10: =SUM(E5:E8) -> 600 | F10: =SUM(F5:F8) -> 600 | G10: =SUM(G5:G8) -> 600 | H10: =SUM(H5:H8) -> 600 | I10: =SUM(I5:I8) -> 600 | ... AE10: =SUM(AE5:AE8) -> 600

Sheet Manutenções
B1: CONTROLE DE MANUTENÇÕES
A2: Item | B2: Data | C2: Em ordem? S/N | D2: Descrição | E2: Providências | F2: Valor
A4: Extintores
A5: Luz de emergência
A6: Iluminação
A7: Interfones
A8: Lixeira
A9: Escadarias
A10: Pinturas
A11: Cerca Elétrica
A12: Limpeza geral | B12: 45366 | D12: lavagem da garagem | F12: 100
B13: 45387 | D13: lavagem da garagem
B14: 45415 | D14: Lavagem da garagem
B15: 45450 | D15: lavagem da garagem
A18: Detetização
A19: Garagem
A20: Piso
A21: Sistema de segurança (câmeras)
A22: Instalações de gás
A23: Caixa de luz
A24: Pintura fachadas
A25: OUTROS
